acquire_zarr/__init__.cp313-win_amd64.pyd
acquire_zarr/__init__.pyi
acquire_zarr/py.typed
acquire_zarr-0.6.0.dist-info/licenses/LICENSE
acquire_zarr-0.6.0.dist-info/METADATA
acquire_zarr-0.6.0.dist-info/WHEEL
acquire_zarr-0.6.0.dist-info/top_level.txt
acquire_zarr-0.6.0.dist-info/RECORD
