Metadata-Version: 2.4
Name: acquire-zarr
Version: 0.6.0
Summary: Performant streaming to Zarr storage, on filesystem or cloud
Author-email: Alan Liddell <aliddell@chanzuckerberg.com>
Requires-Python: >=3.9
License-File: LICENSE
Provides-Extra: testing
Requires-Dist: black; extra == "testing"
Requires-Dist: dask; extra == "testing"
Requires-Dist: mypy; extra == "testing"
Requires-Dist: ome-zarr; extra == "testing"
Requires-Dist: pytest>=7; extra == "testing"
Requires-Dist: pytest-cov; extra == "testing"
Requires-Dist: python-dotenv; extra == "testing"
Requires-Dist: ruff; extra == "testing"
Requires-Dist: s3fs; extra == "testing"
Requires-Dist: scikit-image; extra == "testing"
Requires-Dist: tifffile; extra == "testing"
Requires-Dist: zarr>=3.0.0; extra == "testing"
Dynamic: license-file
